MANIFEST.in
README.md
requirements.txt
setup.cfg
setup.py
spydy/__init__.py
spydy/component.py
spydy/defaults.py
spydy/engine.py
spydy/exceptions.py
spydy/filters.py
spydy/logs.py
spydy/main.py
spydy/mixins.py
spydy/parsers.py
spydy/request.py
spydy/store.py
spydy/urls.py
spydy/utils.py
spydy.egg-info/PKG-INFO
spydy.egg-info/SOURCES.txt
spydy.egg-info/dependency_links.txt
spydy.egg-info/entry_points.txt
spydy.egg-info/requires.txt
spydy.egg-info/top_level.txt