Metadata-Version: 2.1
Name: spydy
Version: 0.1.23
Summary: light-weight high-level web-crawling framework
Home-page: https://github.com/superjcd/spydy
Author: Jiang Chaodi
Author-email: 929760274@qq.com
License: BSD
Download-URL: https://github.com/superjcd/spydy/tarball/0.1.23
Platform: UNKNOWN
Classifier: Development Status :: 3 - Alpha
Classifier: Intended Audience :: Developers
Classifier: Programming Language :: Python :: 3
